NetHyTech_STT/__init__.py
NetHyTech_STT-0.4.dist-info/METADATA
NetHyTech_STT-0.4.dist-info/WHEEL
NetHyTech_STT-0.4.dist-info/entry_points.txt
NetHyTech_STT-0.4.dist-info/top_level.txt
NetHyTech_STT-0.4.dist-info/RECORD
