Metadata-Version: 2.1
Name: NetHyTech-STT
Version: 0.4
Summary: NetHyTech-STT: Convert Speech to Text with Ease!
Home-page: https://github.com/Anubhavchaturvedi/NetHyTech-STT
Author: Anubhav Chaturvedi
Author-email: chaturvedianubhav520@example.com
Project-URL: Source Code, https://github.com/AnubhavChaturvedi-GitHub/NetHyTech_STT.git
Project-URL: Demo Video, https://www.youtube.com/channel/UC7YDMgu0dMRZotLMuB3oEcQ
Classifier: Development Status :: 5 - Production/Stable
Classifier: Intended Audience :: Developers
Classifier: Topic :: Multimedia :: Sound/Audio :: Speech
Classifier: License :: OSI Approved :: MIT License
Classifier: Programming Language :: Python :: 3
Classifier: Programming Language :: Python :: 3.8
Classifier: Programming Language :: Python :: 3.9
Classifier: Operating System :: OS Independent
Requires-Python: >=3.8
Requires-Dist: selenium
Requires-Dist: webdriver-manager
